mapped_enum/__init__.py
mapped_enum-0.3.2.dist-info/LICENSE
mapped_enum-0.3.2.dist-info/METADATA
mapped_enum-0.3.2.dist-info/WHEEL
mapped_enum-0.3.2.dist-info/top_level.txt
mapped_enum-0.3.2.dist-info/RECORD
