Metadata-Version: 2.1
Name: mapped-enum
Version: 0.3.2
Summary: Enums with arbitrary lookup tables
Home-page: https://github.com/zacharied/mapped-enum
Author: Zach Day
Author-email: z@zach.gdn
License: UNKNOWN
Platform: UNKNOWN
Classifier: Intended Audience :: Developers
Classifier: License :: OSI Approved :: MIT License
Classifier: Topic :: Software Development
Classifier: Programming Language :: Python :: 3
Classifier: Operating System :: OS Independent
